statuspageio/__init__.py
statuspageio/client.py
statuspageio/configuration.py
statuspageio/errors.py
statuspageio/http_client.py
statuspageio/services.py
statuspageio/version.py
vukomir_statuspageio-0.0.4.dist-info/LICENSE
vukomir_statuspageio-0.0.4.dist-info/METADATA
vukomir_statuspageio-0.0.4.dist-info/WHEEL
vukomir_statuspageio-0.0.4.dist-info/top_level.txt
vukomir_statuspageio-0.0.4.dist-info/RECORD
